Workbook

Sheet Raw Data
A1: NZX COMPS — RAW DATA
A2: Source: NZX / Company Annual Reports (FY2024 actuals, NZD millions unless noted)
A4: Ticker | B4: Company Name | C4: Sector | D4: Share Price (NZD) | E4: Shares Outstanding (mm) | F4: Revenue ($mm) | G4: EBITDA ($mm) | H4: EBIT ($mm) | I4: Net Income ($mm) | J4: Total Debt ($mm) | K4: Cash ($mm) | L4: CapEx ($mm) | M4: Depreciation ($mm)
A5: FPH | B5: Fisher & Paykel Healthcare | C5: Healthcare | D5: 24.5 | E5: 577 | F5: 1827 | G5: 478 | H5: 373 | I5: 310 | J5: 285 | K5: 312 | L5: 115 | M5: 105
A6: MEL | B6: Meridian Energy | C6: Utilities | D6: 5.62 | E6: 2753 | F6: 2103 | G6: 1210 | H6: 890 | I6: 602 | J6: 2880 | K6: 89 | L6: 340 | M6: 320
A7: AIA | B7: Auckland Intl Airport | C7: Infrastructure | D7: 7.85 | E7: 1317 | F7: 726 | G7: 503 | H7: 285 | I7: 178 | J7: 2650 | K7: 195 | L7: 380 | M7: 218
A8: SPK | B8: Spark New Zealand | C8: Telecom | D8: 3.21 | E8: 1863 | F8: 3782 | G8: 956 | H8: 446 | I8: 210 | J8: 1920 | K8: 215 | L8: 430 | M8: 510
A9: MFT | B9: Mainfreight | C9: Logistics | D9: 63.4 | E9: 103 | F9: 4980 | G9: 620 | H9: 545 | I9: 382 | J9: 340 | K9: 510 | L9: 210 | M9: 75
A10: RYM | B10: Ryman Healthcare | C10: Healthcare/Property | D10: 4.1 | E10: 685 | F10: 525 | G10: 310 | H10: 105 | I10: 62 | J10: 2900 | K10: 88 | L10: 280 | M10: 205
A12: NOTES
A13: All figures in NZD millions (NZDm) unless otherwise stated.
A14: Share Price as at market close 27-Jun-2026. Shares Outstanding in millions.
A15: RYM Net Income is negative (loss) — shown in parentheses per financial modelling convention.
A16: Source: NZX filings, company annual reports, NZX company pages (FY2024 results).

Sheet Comps Output
A1: NZX COMPARABLE COMPANIES ANALYSIS
A4: Ticker | B4: Company | C4: Sector | D4: Mkt Cap ($mm) | E4: Net Debt ($mm) | F4: EV ($mm) | G4: Revenue ($mm) | H4: EBITDA ($mm) | I4: EBIT ($mm) | J4: Net Income ($mm) | K4: EV/Revenue | L4: EV/EBITDA | M4: EV/EBIT | N4: P/E
A5: FPH | B5: =_xlfn.XLOOKUP(A5,'Raw Data'!$A:$A,'Raw Data'!$B:$B) -> Fisher & Paykel Healthcare | C5: =(_xlfn.XLOOKUP(A5,'Raw Data'!$A:$A,'Raw Data'!$C:$C)) -> Healthcare | D5: =PRODUCT(_xlfn.XLOOKUP(A5,'Raw Data'!$A:$A,'Raw Data'!$D:$E)) -> 14136.5 | E5: {=SUM(_xlfn.XLOOKUP(A5,'Raw Data'!$A:$A,'Raw Data'!$J:$K)*{1,-1})} -> -27 | F5: =D5+E5 -> 14109.5 | G5: {=_xlfn.XLOOKUP($A5,'Raw Data'!$A:$A,'Raw Data'!$F:$I)} -> 1827 | H5: 478 | I5: 373 | J5: 310 | K5: =$F5/G5 -> 7.7227696 | L5: =$F5/H5 -> 29.517782 | M5: =$F5/I5 -> 37.827078 | N5: =$D5/J5 -> 45.601613
A6: MEL | B6: =_xlfn.XLOOKUP(A6,'Raw Data'!$A:$A,'Raw Data'!$B:$B) -> Meridian Energy | C6: =(_xlfn.XLOOKUP(A6,'Raw Data'!$A:$A,'Raw Data'!$C:$C)) -> Utilities | D6: =PRODUCT(_xlfn.XLOOKUP(A6,'Raw Data'!$A:$A,'Raw Data'!$D:$E)) -> 15471.86 | E6: {=SUM(_xlfn.XLOOKUP(A6,'Raw Data'!A:A,'Raw Data'!J:K)*{1,-1})} -> 2791 | F6: =D6+E6 -> 18262.86 | G6: {=_xlfn.XLOOKUP($A6,'Raw Data'!$A:$A,'Raw Data'!$F:$I)} -> 2103 | H6: 1210 | I6: 890 | J6: 602 | K6: =$F6/G6 -> 8.684194 | L6: =$F6/H6 -> 15.093273 | M6: =$F6/I6 -> 20.520067 | N6: =$D6/J6 -> 25.700764
A7: AIA | B7: =_xlfn.XLOOKUP(A7,'Raw Data'!$A:$A,'Raw Data'!$B:$B) -> Auckland Intl Airport | C7: =(_xlfn.XLOOKUP(A7,'Raw Data'!$A:$A,'Raw Data'!$C:$C)) -> Infrastructure | D7: =PRODUCT(_xlfn.XLOOKUP(A7,'Raw Data'!$A:$A,'Raw Data'!$D:$E)) -> 10338.45 | E7: {=SUM(_xlfn.XLOOKUP(A7,'Raw Data'!A:A,'Raw Data'!J:K)*{1,-1})} -> 2455 | F7: =D7+E7 -> 12793.45 | G7: {=_xlfn.XLOOKUP($A7,'Raw Data'!$A:$A,'Raw Data'!$F:$I)} -> 726 | H7: 503 | I7: 285 | J7: 178 | K7: =$F7/G7 -> 17.621832 | L7: =$F7/H7 -> 25.434294 | M7: =$F7/I7 -> 44.889298 | N7: =$D7/J7 -> 58.08118
A8: SPK | B8: =_xlfn.XLOOKUP(A8,'Raw Data'!$A:$A,'Raw Data'!$B:$B) -> Spark New Zealand | C8: =(_xlfn.XLOOKUP(A8,'Raw Data'!$A:$A,'Raw Data'!$C:$C)) -> Telecom | D8: =PRODUCT(_xlfn.XLOOKUP(A8,'Raw Data'!$A:$A,'Raw Data'!$D:$E)) -> 5980.23 | E8: {=SUM(_xlfn.XLOOKUP(A8,'Raw Data'!A:A,'Raw Data'!J:K)*{1,-1})} -> 1705 | F8: =D8+E8 -> 7685.23 | G8: {=_xlfn.XLOOKUP($A8,'Raw Data'!$A:$A,'Raw Data'!$F:$I)} -> 3782 | H8: 956 | I8: 446 | J8: 210 | K8: =$F8/G8 -> 2.0320545 | L8: =$F8/H8 -> 8.0389435 | M8: =$F8/I8 -> 17.231457 | N8: =$D8/J8 -> 28.477286
A9: MFT | B9: =_xlfn.XLOOKUP(A9,'Raw Data'!$A:$A,'Raw Data'!$B:$B) -> Mainfreight | C9: =(_xlfn.XLOOKUP(A9,'Raw Data'!$A:$A,'Raw Data'!$C:$C)) -> Logistics | D9: =PRODUCT(_xlfn.XLOOKUP(A9,'Raw Data'!$A:$A,'Raw Data'!$D:$E)) -> 6530.2 | E9: {=SUM(_xlfn.XLOOKUP(A9,'Raw Data'!A:A,'Raw Data'!J:K)*{1,-1})} -> -170 | F9: =D9+E9 -> 6360.2 | G9: {=_xlfn.XLOOKUP($A9,'Raw Data'!$A:$A,'Raw Data'!$F:$I)} -> 4980 | H9: 620 | I9: 545 | J9: 382 | K9: =$F9/G9 -> 1.2771486 | L9: =$F9/H9 -> 10.258387 | M9: =$F9/I9 -> 11.670092 | N9: =$D9/J9 -> 17.094764
A10: RYM | B10: =_xlfn.XLOOKUP(A10,'Raw Data'!$A:$A,'Raw Data'!$B:$B) -> Ryman Healthcare | C10: =(_xlfn.XLOOKUP(A10,'Raw Data'!$A:$A,'Raw Data'!$C:$C)) -> Healthcare/Property | D10: =PRODUCT(_xlfn.XLOOKUP(A10,'Raw Data'!$A:$A,'Raw Data'!$D:$E)) -> 2808.5 | E10: {=SUM(_xlfn.XLOOKUP(A10,'Raw Data'!A:A,'Raw Data'!J:K)*{1,-1})} -> 2812 | F10: =D10+E10 -> 5620.5 | G10: {=_xlfn.XLOOKUP($A10,'Raw Data'!$A:$A,'Raw Data'!$F:$I)} -> 525 | H10: 310 | I10: 105 | J10: 62 | K10: =$F10/G10 -> 10.705714 | L10: =$F10/H10 -> 18.130645 | M10: =$F10/I10 -> 53.528571 | N10: =$D10/J10 -> 45.298387
A11: Mean | D11: =AVERAGE(D5:D10) -> 9210.9567 | E11: =AVERAGE(E5:E10) -> 1594.3333 | F11: =AVERAGE(F5:F10) -> 10805.29 | G11: =AVERAGE(G5:G10) -> 2323.8333 | H11: =AVERAGE(H5:H10) -> 679.5 | I11: =AVERAGE(I5:I10) -> 440.66667 | J11: =AVERAGE(J5:J10) -> 290.66667 | K11: =AVERAGE(K5:K10) -> 8.0072855 | ... N11: =AVERAGE(N5:N10) -> 36.708999
A12: Median | D12: =MEDIAN(D5:D10) -> 8434.325 | E12: =MEDIAN(E5:E10) -> 2080 | F12: =MEDIAN(F5:F10) -> 10239.34 | G12: =MEDIAN(G5:G10) -> 1965 | H12: =MEDIAN(H5:H10) -> 561.5 | I12: =MEDIAN(I5:I10) -> 409.5 | J12: =MEDIAN(J5:J10) -> 260 | K12: =MEDIAN(K5:K10) -> 8.2034818 | ... N12: =MEDIAN(N5:N10) -> 36.887836
